nerd/__init__.py
nerd/client.py
nerd/nerd_client.py
nerd/nerd_client_batch.py
entity_fishing_client-0.7.2.dist-info/LICENSE.txt
entity_fishing_client-0.7.2.dist-info/METADATA
entity_fishing_client-0.7.2.dist-info/WHEEL
entity_fishing_client-0.7.2.dist-info/top_level.txt
entity_fishing_client-0.7.2.dist-info/RECORD
