Metadata-Version: 2.1
Name: entity-fishing-client
Version: 0.7.2
Summary: A minimal client for entity-fishing service.
Home-page: https://github.com/Hirmeos/entity-fishing-client-python
Author: Francesco de Virgilio, Luca Foppiano
Author-email: francesco.devirgilio@ubiquitypress.com, luca.foppiano@inria.fr
License: Apache 2.0
Keywords: named entity recognition,entity matching,entity recognition
Classifier: Development Status :: 4 - Beta
Classifier: Intended Audience :: Developers
Classifier: License :: OSI Approved :: Apache Software License
Classifier: Programming Language :: Python :: 2.7
Classifier: Programming Language :: Python :: 3.6
License-File: LICENSE.txt
Requires-Dist: requests
Requires-Dist: zenlog
